funq/__init__.py
funq/aliases-gkits.conf
funq/aliases.py
funq/client.py
funq/errors.py
funq/models.py
funq/noseplugin.py
funq/screenshoter.py
funq/testcase.py
funq/tools.py
funq/tests/__init__.py
funq/tests/test_aliases.py
funq/tests/test_client.py
funq/tests/test_models.py
funq/tests/test_noseplugin.py
funq/tests/test_screenshoter.py
funq/tests/test_tools.py
funq-1.2.0.dist-info/LICENCE-fr.txt
funq-1.2.0.dist-info/LICENCE.txt
funq-1.2.0.dist-info/METADATA
funq-1.2.0.dist-info/WHEEL
funq-1.2.0.dist-info/entry_points.txt
funq-1.2.0.dist-info/top_level.txt
funq-1.2.0.dist-info/RECORD
