Metadata-Version: 2.1
Name: funq
Version: 1.2.0
Summary: write FUNctional tests for Qt applications (client)
Home-page: https://github.com/parkouss/funq
Author: Julien Pagès
Author-email: j.parkouss@gmail.com
License: UNKNOWN
Platform: UNKNOWN
Requires-Dist: nose
